<?xml version="1.0" encoding="utf-8"?><content><item><path>images/tech.jpg</path><description><![CDATA[Software Events]]></description><action>navigate</action><param>../corona_13/software/index.html,_self</param></item><item><path>images/elect.jpg</path><description><![CDATA[Electronics Events]]></description><action>navigate</action><param>../corona_13/electronics/index.html,_self</param></item><item><path>images/battle.jpg</path><description><![CDATA[Battle Of bands!! ]]></description><action>navigate</action></item><item><path>images/cult.jpg</path><description><![CDATA[Cultural Events]]></description><action>navigate</action><param>../corona_13/cultural/index.html,_self</param></item><item><path>images/lit.jpg</path><description><![CDATA[Literary Events]]></description><action>navigate</action><param>../corona_13/literary/index.html,_self</param></item><item><path>images/fine.jpg</path><description><![CDATA[Fine arts]]></description><action>navigate</action><param>../corona_13/fine/index.html,_self</param></item><item><path>images/online.jpg</path><description><![CDATA[Online Events]]></description><action>navigate</action><param>../corona_13/online/index.html,_self</param></item><item><path>images/lan.jpg</path><description><![CDATA[Gaming Events]]></description><action>navigate</action><param>../corona_13/online/index.html,_self</param></item><item><path>images/fun.jpg</path><description><![CDATA[Funzone]]></description><action>navigate</action><param>../corona_13/fun/index.html,_self</param></item><item><path>images/star.png</path><description><![CDATA[Rabbi Shergill With Band On 23 March!!]]></description><action>navigate</action><param>../corona_13/star/index.html,_self</param></item><item><path>images/workshop.jpg</path><description><![CDATA[Workshop]]></description><action>navigate</action><param>../corona_13/workshop/index.html,_self</param></item></content>
